phovea_data_redis/__init__.py
phovea_data_redis/assigner.py
phovea_data_redis/bytes_to_string_encoder.py
phovea_data_redis/cache.py
phovea_data_redis/config.json
phovea_data_redis/load.py
phovea_data_redis/mapping_table.py
phovea_data_redis/utils.py
phovea_data_redis-8.0.0.dist-info/LICENSE
phovea_data_redis-8.0.0.dist-info/METADATA
phovea_data_redis-8.0.0.dist-info/WHEEL
phovea_data_redis-8.0.0.dist-info/entry_points.txt
phovea_data_redis-8.0.0.dist-info/top_level.txt
phovea_data_redis-8.0.0.dist-info/RECORD
